{
  "table_type": "Flat-Entity",
  "entity_types": [
    "Healthcare"
  ],
  "relation_types": [
    "HAS_ATTRIBUTE"
  ],
  "column_roles": {
    "经济体": "metadata",
    "参照年份": "value",
    "整体医疗卫生经常性开支相对本地生产总值的百分比(%)": "subject",
    "公共医疗卫生经常性开支相对本地生产总值的百分比 (%)": "subject",
    "私人医疗卫生经常性开支相对本地生产总值的百分比 (%)": "subject",
    "整体公共开支相对本地生产总值的百分比 (%)": "subject",
    "公共医疗卫生经常性开支相对税收的百分比 (%)": "subject",
    "最高个人入息税边际税率* (%) 截至2025年9月": "subject",
    "销售税率(%) 截至2025年9月": "subject",
    "税收收入相对本地生产总值的百分比 (%)": "subject",
    "人口 (百万)": "value",
    "65岁及以上人口百分比": "subject"
  },
  "entity_extraction_template": "For each row, extract the value of '整体医疗卫生经常性开支相对本地生产总值的百分比(%)' as a Healthcare entity node.",
  "relation_extraction_template": "For each Healthcare entity, create HAS_ATTRIBUTE relations to numeric values in columns: \"参照年份\", \"人口 (百万)\".",
  "extraction_constraints": [
    "Each row represents one distinct Healthcare entity.",
    "Use '整体医疗卫生经常性开支相对本地生产总值的百分比(%)' as the entity identifier.",
    "Numeric columns become attribute values linked via HAS_ATTRIBUTE.",
    "Skip rows where the subject column is empty or null."
  ],
  "parsed_time_headers": []
}